frzpop/__init__.py
frzpop/additives.py
frzpop/chords.py
frzpop/dynamics.py
frzpop/feet.py
frzpop/freezers.py
frzpop/machines.py
frzpop/notes.py
frzpop/quantize.py
frzpop/scales.py
frzpop/shuffle.py
frzpop-0.4.2.dist-info/LICENSE
frzpop-0.4.2.dist-info/METADATA
frzpop-0.4.2.dist-info/WHEEL
frzpop-0.4.2.dist-info/top_level.txt
frzpop-0.4.2.dist-info/RECORD
