Metadata-Version: 2.1
Name: frzpop
Version: 0.4.2
Summary: Generates MIDI files
Home-page: https://github.com/tsmorrill/Freeze-Pop
Author: T Morrill
Author-email: morrill.math@gmail.com
License: MIT
License-File: LICENSE
Requires-Dist: midiutil (>=1.2.1)
